ipyobservable/__init__.py
ipyobservable/_version.py
ipyobservable/magics.py
ipyobservable/observable.py
ipyobservable/labextension/package.json
ipyobservable/labextension/static/163.e92448205951f2cf07c6.js
ipyobservable/labextension/static/181.a4da644902f5fa59d0cb.js
ipyobservable/labextension/static/261.218301f4c4842978ae6b.js
ipyobservable/labextension/static/261.f071a3cc422072b3a676.js
ipyobservable/labextension/static/608.6e725711f4a31fd05dce.js
ipyobservable/labextension/static/767.0969cc8ff3521c2de5a7.js
ipyobservable/labextension/static/767.cbb3f9a51b181ff19541.js
ipyobservable/labextension/static/remoteEntry.53cda1f3b9dc59618a21.js
ipyobservable/labextension/static/remoteEntry.6b13df70b220866a0d77.js
ipyobservable/labextension/static/style.js
ipyobservable/labextension/static/third-party-licenses.json
ipyobservable/nbextension/extension.js
ipyobservable/nbextension/index.js
ipyobservable-0.1.2.data/data/etc/jupyter/nbconfig/notebook.d/ipyobservable.json
ipyobservable-0.1.2.data/data/share/jupyter/labextensions/ipyobservable/install.json
ipyobservable-0.1.2.data/data/share/jupyter/labextensions/ipyobservable/package.json
ipyobservable-0.1.2.data/data/share/jupyter/labextensions/ipyobservable/static/163.e92448205951f2cf07c6.js
ipyobservable-0.1.2.data/data/share/jupyter/labextensions/ipyobservable/static/181.a4da644902f5fa59d0cb.js
ipyobservable-0.1.2.data/data/share/jupyter/labextensions/ipyobservable/static/261.218301f4c4842978ae6b.js
ipyobservable-0.1.2.data/data/share/jupyter/labextensions/ipyobservable/static/608.6e725711f4a31fd05dce.js
ipyobservable-0.1.2.data/data/share/jupyter/labextensions/ipyobservable/static/767.0969cc8ff3521c2de5a7.js
ipyobservable-0.1.2.data/data/share/jupyter/labextensions/ipyobservable/static/remoteEntry.6b13df70b220866a0d77.js
ipyobservable-0.1.2.data/data/share/jupyter/labextensions/ipyobservable/static/style.js
ipyobservable-0.1.2.data/data/share/jupyter/labextensions/ipyobservable/static/third-party-licenses.json
ipyobservable-0.1.2.dist-info/METADATA
ipyobservable-0.1.2.dist-info/WHEEL
ipyobservable-0.1.2.dist-info/top_level.txt
ipyobservable-0.1.2.dist-info/RECORD
